Quaternion/Quaternion.py
Quaternion/__init__.py
Quaternion/tests/__init__.py
Quaternion/tests/test.py
Quaternion/tests/test_all.py
Quaternion/tests/data/quaternion-v3.4.1.pkl
Quaternion-3.5.2.post4.dist-info/LICENSE.rst
Quaternion-3.5.2.post4.dist-info/METADATA
Quaternion-3.5.2.post4.dist-info/WHEEL
Quaternion-3.5.2.post4.dist-info/top_level.txt
Quaternion-3.5.2.post4.dist-info/RECORD
